{
  "vipendtime": "2026-04-23 04:00:05",
  "cookie": "user_type=0; 1&_device=iPhone&b33543f5-6a56-4245-a258-7ec94bc291dd&2.25.1; x-intl-mulehorse-bucketIds=%2C; net-mode=WIFI; channel=ios-appstore; country_id=1; idfa=40cb2a31-be6b-46de-ac4d-ce74e6099f8a; domain=apisg.himalaya.com; appsflyer_id=1776877201-1111111; locale=zh_CN; path=/; 1&_token=10007249083&8d80c79c01f64046b70b77502db5bdc48724; location=sg; impl=com.ximalaya.xmlyi; x-abtest-bucketIds=; JSESSIONID=",
  "email": "645329112@gmail.com",
  "uid": 10007249083,
  "token": "8d80c79c01f64046b70b77502db5bdc48724"
}