{
  "vipendtime": "2026-07-20 01:00:04",
  "cookie": "user_type=0; 1&_device=iPhone&8d44c40b-073b-4d90-84b5-a38b80facea6&2.25.1; x-intl-mulehorse-bucketIds=%2C; net-mode=WIFI; channel=ios-appstore; country_id=1; idfa=33d9f5df-643e-480f-8619-7604d448bf3a; domain=apisg.himalaya.com; appsflyer_id=1784469601-1111111; locale=zh_CN; path=/; 1&_token=10007342548&3e1c717f07f520402e08818036e4187405e5; location=sg; impl=com.ximalaya.xmlyi; x-abtest-bucketIds=; JSESSIONID=",
  "email": "176386303@gmail.com",
  "uid": 10007342548,
  "token": "3e1c717f07f520402e08818036e4187405e5"
}