{
  "vipendtime": "2026-07-23 09:00:04",
  "cookie": "user_type=0; 1&_device=iPhone&1860c9ea-82ce-493c-beec-ffe3d94bf198&2.25.1; x-intl-mulehorse-bucketIds=%2C; net-mode=WIFI; channel=ios-appstore; country_id=1; idfa=01987bb6-21a4-491d-b8e3-167a27bf0754; domain=apisg.himalaya.com; appsflyer_id=1784757601-1111111; locale=zh_CN; path=/; 1&_token=10007344397&b8cf4aff0e63004ccf08d740424d9ac90bd1; location=sg; impl=com.ximalaya.xmlyi; x-abtest-bucketIds=; JSESSIONID=",
  "email": "363182998@gmail.com",
  "uid": 10007344397,
  "token": "b8cf4aff0e63004ccf08d740424d9ac90bd1"
}