{
  "vipendtime": "2026-07-08 23:00:04",
  "cookie": "user_type=0; 1&_device=iPhone&dd47d344-4cd8-4b66-8912-bd3c600eca10&2.25.1; x-intl-mulehorse-bucketIds=%2C; net-mode=WIFI; channel=ios-appstore; country_id=1; idfa=7738dd45-0b25-4d38-9b75-f30cc8499459; domain=apisg.himalaya.com; appsflyer_id=1783512001-1111111; locale=zh_CN; path=/; 1&_token=10007336682&bb25b63f06194048c30b92a03631f5d5df69; location=sg; impl=com.ximalaya.xmlyi; x-abtest-bucketIds=; JSESSIONID=",
  "email": "347232285@gmail.com",
  "uid": 10007336682,
  "token": "bb25b63f06194048c30b92a03631f5d5df69"
}