{
  "vipendtime": "2026-04-20 08:00:06",
  "cookie": "user_type=0; 1&_device=iPhone&1b693843-8f9a-40ca-9869-ca12d4c4799c&2.25.1; x-intl-mulehorse-bucketIds=%2C; net-mode=WIFI; channel=ios-appstore; country_id=1; idfa=048e03ca-a018-463c-9403-6fdf0b3d3272; domain=apisg.himalaya.com; appsflyer_id=1776632400-1111111; locale=zh_CN; path=/; 1&_token=10007245246&e37c2fc2054a1048dd089250d64c2f20031b; location=sg; impl=com.ximalaya.xmlyi; x-abtest-bucketIds=; JSESSIONID=",
  "email": "323019322@gmail.com",
  "uid": 10007245246,
  "token": "e37c2fc2054a1048dd089250d64c2f20031b"
}