{
  "vipendtime": "2026-04-24 06:00:07",
  "cookie": "user_type=0; 1&_device=iPhone&5cbc78fa-fb5a-4228-b1f1-ff7c84907dc8&2.25.1; x-intl-mulehorse-bucketIds=%2C; net-mode=WIFI; channel=ios-appstore; country_id=1; idfa=1ebc77a5-e7b3-403f-8beb-0d0257339d91; domain=apisg.himalaya.com; appsflyer_id=1776970801-1111111; locale=zh_CN; path=/; 1&_token=10007250573&2a22ec7401dbc04e7e0aec903edd12fe903e; location=sg; impl=com.ximalaya.xmlyi; x-abtest-bucketIds=; JSESSIONID=",
  "email": "198187910@gmail.com",
  "uid": 10007250573,
  "token": "2a22ec7401dbc04e7e0aec903edd12fe903e"
}