{
  "vipendtime": "2026-07-20 21:00:04",
  "cookie": "user_type=0; 1&_device=iPhone&c426aaf5-f7fc-41d1-a544-661853511a96&2.25.1; x-intl-mulehorse-bucketIds=%2C; net-mode=WIFI; channel=ios-appstore; country_id=1; idfa=feb0495b-faee-47bf-9bce-9facd5bfc5d0; domain=apisg.himalaya.com; appsflyer_id=1784541601-1111111; locale=zh_CN; path=/; 1&_token=10007342956&ed25bb71055dd0499f0b1120b0eed039c003; location=sg; impl=com.ximalaya.xmlyi; x-abtest-bucketIds=; JSESSIONID=",
  "email": "341369930@gmail.com",
  "uid": 10007342956,
  "token": "ed25bb71055dd0499f0b1120b0eed039c003"
}