{
  "vipendtime": "2026-04-03 13:00:12",
  "cookie": "user_type=0; 1&_device=iPhone&90bc5523-9a7a-4554-863d-8d378998e63b&2.25.1; x-intl-mulehorse-bucketIds=%2C; net-mode=WIFI; channel=ios-appstore; country_id=1; idfa=7ab4cc6e-096f-4ea3-91cc-0171ad9695df; domain=apisg.himalaya.com; appsflyer_id=1775181600-1111111; locale=zh_CN; path=/; 1&_token=10007224632&62d7f6df09fe7047d50bfbf0e93039e709ea; location=sg; impl=com.ximalaya.xmlyi; x-abtest-bucketIds=; JSESSIONID=",
  "email": "186908114@gmail.com",
  "uid": 10007224632,
  "token": "62d7f6df09fe7047d50bfbf0e93039e709ea"
}