{
  "vipendtime": "2026-07-04 09:00:04",
  "cookie": "user_type=0; 1&_device=iPhone&429de081-a08d-47d7-93d4-7a8cc080375a&2.25.1; x-intl-mulehorse-bucketIds=%2C; net-mode=WIFI; channel=ios-appstore; country_id=1; idfa=da6426cc-4cfb-4c80-b6ee-6b55b2a45ddf; domain=apisg.himalaya.com; appsflyer_id=1783116001-1111111; locale=zh_CN; path=/; 1&_token=10007334252&75e14e5d0d3880474d09bc10124fce522bdf; location=sg; impl=com.ximalaya.xmlyi; x-abtest-bucketIds=; JSESSIONID=",
  "email": "215267735@gmail.com",
  "uid": 10007334252,
  "token": "75e14e5d0d3880474d09bc10124fce522bdf"
}