{
  "vipendtime": "2026-04-13 16:00:04",
  "cookie": "user_type=0; 1&_device=iPhone&204b567d-08b5-472b-8d1d-ae93b0a6e84b&2.25.1; x-intl-mulehorse-bucketIds=%2C; net-mode=WIFI; channel=ios-appstore; country_id=1; idfa=3fb4e136-91cd-4e0d-bca8-a4fc804c0b88; domain=apisg.himalaya.com; appsflyer_id=1776056401-1111111; locale=zh_CN; path=/; 1&_token=10007236696&66920c400810e041d20a01b0ba4c2a0e8eb1; location=sg; impl=com.ximalaya.xmlyi; x-abtest-bucketIds=; JSESSIONID=",
  "email": "578442192@gmail.com",
  "uid": 10007236696,
  "token": "66920c400810e041d20a01b0ba4c2a0e8eb1"
}