{
  "vipendtime": "2026-07-21 07:00:04",
  "cookie": "user_type=0; 1&_device=iPhone&5ca2a280-17c2-4062-924d-b0f6e5aa3433&2.25.1; x-intl-mulehorse-bucketIds=%2C; net-mode=WIFI; channel=ios-appstore; country_id=1; idfa=f7a3187d-c088-4ebc-b7ef-9232fc1a4763; domain=apisg.himalaya.com; appsflyer_id=1784577601-1111111; locale=zh_CN; path=/; 1&_token=10007343219&c838060f015d304ea009738030e8a36fe76b; location=sg; impl=com.ximalaya.xmlyi; x-abtest-bucketIds=; JSESSIONID=",
  "email": "264706823@gmail.com",
  "uid": 10007343219,
  "token": "c838060f015d304ea009738030e8a36fe76b"
}